{
  "per_feed": {
    "https://evilgodfahim.github.io/bdlb/final.xml": {
      "fetched": 75,
      "passed_age": 73,
      "capped": 73
    },
    "https://evilgodfahim.github.io/bint/final.xml": {
      "fetched": 100,
      "passed_age": 100,
      "capped": 100
    },
    "https://evilgodfahim.github.io/bdcdb/curated_feed.xml": {
      "fetched": 500,
      "passed_age": 95,
      "capped": 95
    }
  },
  "per_method": {
    "KL": 0,
    "DIRECT": 675
  },
  "total_fetched": 675,
  "total_passed_age": 268,
  "total_new": 250,
  "total_signal_mistral": 12,
  "total_signal": 12,
  "total_signal_deduped": 12,
  "timestamp": "2026-04-12T04:11:26.010026"
}